nonadditivity/README.md
nonadditivity/__init__.py
nonadditivity/classification/README.md
nonadditivity/classification/__init__.py
nonadditivity/classification/circle_classification.py
nonadditivity/classification/classification_classes/README.md
nonadditivity/classification/classification_classes/__init__.py
nonadditivity/classification/classification_classes/circle.py
nonadditivity/classification/classification_classes/compound.py
nonadditivity/classification/classification_classes/transfromation.py
nonadditivity/classification/classify.py
nonadditivity/classification/compound_classification.py
nonadditivity/classification/ortho_classification.py
nonadditivity/classification/rgroup_distance.py
nonadditivity/classification/transformation_classification.py
nonadditivity/classification/utils.py
nonadditivity/cli.py
nonadditivity/nonadditivity_workflow.py
nonadditivity/utils/README.md
nonadditivity/utils/__init__.py
nonadditivity/utils/commandline.py
nonadditivity/utils/errors.py
nonadditivity/utils/log.py
nonadditivity/utils/math.py
nonadditivity/utils/types.py
nonadditivity/workflow/README.md
nonadditivity/workflow/__init__.py
nonadditivity/workflow/canonicalize_output.py
nonadditivity/workflow/input_parsing.py
nonadditivity/workflow/mmpdb_helper.py
nonadditivity/workflow/nonadditivity_core.py
nonadditivity/workflow/output.py
nonadditivity-2.0.1.dist-info/LICENSE
nonadditivity-2.0.1.dist-info/METADATA
nonadditivity-2.0.1.dist-info/WHEEL
nonadditivity-2.0.1.dist-info/entry_points.txt
nonadditivity-2.0.1.dist-info/RECORD
