Metadata-Version: 2.3
Name: nonadditivity
Version: 2.0.1
Summary: A program to find key complex patterns in SAR data
License: LICENSE
Keywords: SAR,Cheminformatics,MMP,RDKit,Nonadditivity
Author: Dr. Christian Kramer
Author-email: christian.kramer@roche.com
Maintainer: Dr. Laura Guasch
Maintainer-email: laura.guasch@roche.com
Requires-Python: >3.9,<3.13
Classifier: Development Status :: 5 - Production/Stable
Classifier: Environment :: Console
Classifier: Framework :: Pytest
Classifier: Intended Audience :: Developers
Classifier: License :: OSI Approved :: BSD License
Classifier: License :: Other/Proprietary License
Classifier: Operating System :: OS Independent
Classifier: Programming Language :: Python
Classifier: Programming Language :: Python :: 3
Classifier: Programming Language :: Python :: 3.10
Classifier: Programming Language :: Python :: 3.11
Classifier: Programming Language :: Python :: 3.12
Classifier: Programming Language :: Python :: 3 :: Only
Classifier: Topic :: Scientific/Engineering :: Artificial Intelligence
Classifier: Topic :: Scientific/Engineering :: Chemistry
Requires-Dist: click (>=8.0.0)
Requires-Dist: mmpdb (==2.1)
Requires-Dist: numpy (>=1.26.0)
Requires-Dist: pandas (>=2.1.1)
Requires-Dist: rdkit (==2024.3.3)
Requires-Dist: scipy (>=1.12.0)
Requires-Dist: tqdm (>=4.65.0)
Requires-Dist: ujson (>=5.8.0)
Project-URL: Bug Tracker, https://github.com/Roche/NonadditivityAnalysis/issues
Project-URL: Repository, https://github.com/Roche/NonadditivityAnalysis
Project-URL: Source Code, https://github.com/Roche/NonadditivityAnalysis/
